setup.py
pyjaco/__init__.py
pyjaco/decorator.py
pyjaco/formater.py
pyjaco.egg-info/PKG-INFO
pyjaco.egg-info/SOURCES.txt
pyjaco.egg-info/dependency_links.txt
pyjaco.egg-info/top_level.txt
pyjaco/compiler/__init__.py
pyjaco/compiler/javascript.py
pyjaco/compiler/multiplexer.py
pyjaco/compiler/python.py