Metadata-Version: 1.0
Name: pyjaco
Version: 1.0.0
Summary: Python to JavaScript translator
Home-page: http://pyjaco.org
Author: Pyjaco development team
Author-email: developer@pyjaco.org
License: UNKNOWN
Keywords: python javascript translator compiler
Platform: UNKNOWN
